securedata/__init__.py
securedata/__main__.py
securedata/mail.py
securedata/securedata.py
securedata-2022.6.22.1.dist-info/LICENSE.md
securedata-2022.6.22.1.dist-info/METADATA
securedata-2022.6.22.1.dist-info/WHEEL
securedata-2022.6.22.1.dist-info/entry_points.txt
securedata-2022.6.22.1.dist-info/top_level.txt
securedata-2022.6.22.1.dist-info/RECORD
