Metadata-Version: 2.1
Name: securedata
Version: 2022.6.22.1
Summary: Easily manage data storage and logging across repos
Home-page: https://github.com/tylerjwoodfin/securedata
Author: Tyler Woodfin
Author-email: tyler@tylerwoodfin.com
License: : OSI Approved :: MIT License
Requires-Python: >=3.6
License-File: LICENSE.md
